tkit_scrapy_mongo/__init__.py
tkit_scrapy_mongo/connection.py
tkit_scrapy_mongo/defaults.py
tkit_scrapy_mongo/dupefilter.py
tkit_scrapy_mongo/picklecompat.py
tkit_scrapy_mongo/pipelines.py
tkit_scrapy_mongo/queue.py
tkit_scrapy_mongo/scheduler.py
tkit_scrapy_mongo/spiders.py
tkit_scrapy_mongo/utils.py
tkit_scrapy_mongo-0.0.0.116654862.dist-info/LICENSE
tkit_scrapy_mongo-0.0.0.116654862.dist-info/METADATA
tkit_scrapy_mongo-0.0.0.116654862.dist-info/WHEEL
tkit_scrapy_mongo-0.0.0.116654862.dist-info/top_level.txt
tkit_scrapy_mongo-0.0.0.116654862.dist-info/RECORD
