Metadata-Version: 2.1
Name: tkit-scrapy-mongo
Version: 0.0.0.116654862
Summary: Terry toolkit sdk for tkit_scrapy_mongo ,
Home-page: https://github.com/napoler/tkit_scrapy_mongo
Author: Terry Chan
Author-email: napoler2008@gmail.com
License: UNKNOWN
Platform: UNKNOWN
License-File: LICENSE
Requires-Dist: pymongo (==3.10.1)
